[[{"elapse_time":-45260,"sport":"Football","event_count":0,"eventID":1090776,"eventTitle":"Detroit Lions at Arizona Cardinals","eventStartDateTime":"March 09, 2019","eventInTime":"16:25","eventInSeconds":"00:00","hasActiveLines":"","sectionType":"NFL","sectionEvent":"NFL - Detroit Lions at Arizona Cardinals","url":"\/live-betting\/nfl\/detroit-lions-at-arizona-cardinals","event":[{"contestantDisplayName":"Detroit Lions","isHomeTeam":false,"rotationNumber":127,"isCircled":false,"hotInfo":"https:\/\/stats.topbet.eu\/stats\/game-by-rotation\/matchup\/nfl\/127","pitcherID":0,"pitcherDisplayName":null,"lines":[{"lineID":499970,"lineType":8,"isLineActive":true,"odds":"-120","overLineValue":0,"underLineValue":0,"pointSpreadValue":null,"alternateLineID":0,"matchupContestant1":"none","matchupOdds1":0,"matchupContestant2":"none","matchupOdds2":0,"isCircled":false,"splitBall":0},{"lineID":1045423,"lineType":9,"isLineActive":true,"odds":"-120","overLineValue":0,"underLineValue":0,"pointSpreadValue":"-2.5","alternateLineID":0,"matchupContestant1":"none","matchupOdds1":0,"matchupContestant2":"none","matchupOdds2":0,"isCircled":false,"splitBall":0,"handicap":[{"handicap":"-2.0","handicapOdds":"-130"},{"handicap":"-1.5","handicapOdds":"-140"},{"handicap":"-1.0","handicapOdds":"-155"},{"handicap":"-0.5","handicapOdds":"-170"},{"handicap":"0.0","handicapOdds":"-185"},{"handicap":"0.5","handicapOdds":"-200"}]},{"lineID":598096,"lineType":2,"isLineActive":true,"odds":-120,"overLineValue":"40.0","underLineValue":0,"pointSpreadValue":null,"alternateLineID":0,"matchupContestant1":"none","matchupOdds1":0,"matchupContestant2":"none","matchupOdds2":0,"isCircled":false,"splitBall":0,"handicap":[{"handicap":"39.5","handicapOdds":"-130"},{"handicap":"39.0","handicapOdds":"-140"},{"handicap":"38.5","handicapOdds":"-155"},{"handicap":"38.0","handicapOdds":"-170"},{"handicap":"37.5","handicapOdds":"-185"},{"handicap":"37.0","handicapOdds":"-200"}]},{"lineID":597838,"lineType":3,"isLineActive":true,"odds":100,"overLineValue":0,"underLineValue":"40.0","pointSpreadValue":null,"alternateLineID":0,"matchupContestant1":"none","matchupOdds1":0,"matchupContestant2":"none","matchupOdds2":0,"isCircled":false,"splitBall":0,"handicap":[{"handicap":"40.5","handicapOdds":"-110"},{"handicap":"41.0","handicapOdds":"-120"},{"handicap":"41.5","handicapOdds":"-135"},{"handicap":"42.0","handicapOdds":"-150"},{"handicap":"42.5","handicapOdds":"-165"},{"handicap":"43.0","handicapOdds":"-180"}]}]},{"contestantDisplayName":"Arizona Cardinals","isHomeTeam":true,"rotationNumber":128,"isCircled":false,"hotInfo":"https:\/\/stats.topbet.eu\/stats\/game-by-rotation\/matchup\/nfl\/128","pitcherID":0,"pitcherDisplayName":null,"lines":[{"lineID":499971,"lineType":8,"isLineActive":true,"odds":"100","overLineValue":0,"underLineValue":0,"pointSpreadValue":null,"alternateLineID":0,"matchupContestant1":"none","matchupOdds1":0,"matchupContestant2":"none","matchupOdds2":0,"isCircled":false,"splitBall":0},{"lineID":1045424,"lineType":9,"isLineActive":true,"odds":"100","overLineValue":0,"underLineValue":0,"pointSpreadValue":"2.5","alternateLineID":0,"matchupContestant1":"none","matchupOdds1":0,"matchupContestant2":"none","matchupOdds2":0,"isCircled":false,"splitBall":0,"handicap":[{"handicap":"3.0","handicapOdds":"-125"},{"handicap":"3.5","handicapOdds":"-150"},{"handicap":"4.0","handicapOdds":"-165"},{"handicap":"4.5","handicapOdds":"-180"},{"handicap":"5.0","handicapOdds":"-195"},{"handicap":"5.5","handicapOdds":"-210"}]},{"lineID":598096,"lineType":2,"isLineActive":true,"odds":-120,"overLineValue":"40.0","underLineValue":0,"pointSpreadValue":null,"alternateLineID":0,"matchupContestant1":"none","matchupOdds1":0,"matchupContestant2":"none","matchupOdds2":0,"isCircled":false,"splitBall":0,"handicap":[{"handicap":"39.5","handicapOdds":"-130"},{"handicap":"39.0","handicapOdds":"-140"},{"handicap":"38.5","handicapOdds":"-155"},{"handicap":"38.0","handicapOdds":"-170"},{"handicap":"37.5","handicapOdds":"-185"},{"handicap":"37.0","handicapOdds":"-200"}]},{"lineID":597838,"lineType":3,"isLineActive":true,"odds":100,"overLineValue":0,"underLineValue":"40.0","pointSpreadValue":null,"alternateLineID":0,"matchupContestant1":"none","matchupOdds1":0,"matchupContestant2":"none","matchupOdds2":0,"isCircled":false,"splitBall":0,"handicap":[{"handicap":"40.5","handicapOdds":"-110"},{"handicap":"41.0","handicapOdds":"-120"},{"handicap":"41.5","handicapOdds":"-135"},{"handicap":"42.0","handicapOdds":"-150"},{"handicap":"42.5","handicapOdds":"-165"},{"handicap":"43.0","handicapOdds":"-180"}]}]}]},{"elapse_time":-45260,"sport":"Football","event_count":0,"eventID":1090777,"eventTitle":"Philadelphia Eagles at Dallas Cowboys","eventStartDateTime":"March 09, 2019","eventInTime":"16:25","eventInSeconds":"00:00","hasActiveLines":"","sectionType":"NFL","sectionEvent":"NFL - Philadelphia Eagles at Dallas Cowboys","url":"\/live-betting\/nfl\/philadelphia-eagles-at-dallas-cowboys","event":[{"contestantDisplayName":"Philadelphia Eagles","isHomeTeam":false,"rotationNumber":129,"isCircled":false,"hotInfo":"https:\/\/stats.topbet.eu\/stats\/game-by-rotation\/matchup\/nfl\/129","pitcherID":0,"pitcherDisplayName":null,"lines":[{"lineID":499972,"lineType":8,"isLineActive":true,"odds":"-125","overLineValue":0,"underLineValue":0,"pointSpreadValue":null,"alternateLineID":0,"matchupContestant1":"none","matchupOdds1":0,"matchupContestant2":"none","matchupOdds2":0,"isCircled":false,"splitBall":0},{"lineID":1045425,"lineType":9,"isLineActive":true,"odds":"-125","overLineValue":0,"underLineValue":0,"pointSpreadValue":"-2.0","alternateLineID":0,"matchupContestant1":"none","matchupOdds1":0,"matchupContestant2":"none","matchupOdds2":0,"isCircled":false,"splitBall":0,"handicap":[{"handicap":"-1.5","handicapOdds":"-135"},{"handicap":"-1.0","handicapOdds":"-145"},{"handicap":"-0.5","handicapOdds":"-160"},{"handicap":"0.0","handicapOdds":"-175"},{"handicap":"0.5","handicapOdds":"-190"},{"handicap":"1.0","handicapOdds":"-205"}]},{"lineID":598097,"lineType":2,"isLineActive":true,"odds":-120,"overLineValue":"30.0","underLineValue":0,"pointSpreadValue":null,"alternateLineID":0,"matchupContestant1":"none","matchupOdds1":0,"matchupContestant2":"none","matchupOdds2":0,"isCircled":false,"splitBall":0,"handicap":[{"handicap":"29.5","handicapOdds":"-130"},{"handicap":"29.0","handicapOdds":"-140"},{"handicap":"28.5","handicapOdds":"-155"},{"handicap":"28.0","handicapOdds":"-170"},{"handicap":"27.5","handicapOdds":"-185"},{"handicap":"27.0","handicapOdds":"-200"}]},{"lineID":597839,"lineType":3,"isLineActive":true,"odds":100,"overLineValue":0,"underLineValue":"30.0","pointSpreadValue":null,"alternateLineID":0,"matchupContestant1":"none","matchupOdds1":0,"matchupContestant2":"none","matchupOdds2":0,"isCircled":false,"splitBall":0,"handicap":[{"handicap":"30.5","handicapOdds":"-110"},{"handicap":"31.0","handicapOdds":"-120"},{"handicap":"31.5","handicapOdds":"-135"},{"handicap":"32.0","handicapOdds":"-150"},{"handicap":"32.5","handicapOdds":"-165"},{"handicap":"33.0","handicapOdds":"-180"}]}]},{"contestantDisplayName":"Dallas Cowboys","isHomeTeam":true,"rotationNumber":130,"isCircled":false,"hotInfo":"https:\/\/stats.topbet.eu\/stats\/game-by-rotation\/matchup\/nfl\/130","pitcherID":0,"pitcherDisplayName":null,"lines":[{"lineID":499973,"lineType":8,"isLineActive":true,"odds":"105","overLineValue":0,"underLineValue":0,"pointSpreadValue":null,"alternateLineID":0,"matchupContestant1":"none","matchupOdds1":0,"matchupContestant2":"none","matchupOdds2":0,"isCircled":false,"splitBall":0},{"lineID":1045426,"lineType":9,"isLineActive":true,"odds":"105","overLineValue":0,"underLineValue":0,"pointSpreadValue":"2.0","alternateLineID":0,"matchupContestant1":"none","matchupOdds1":0,"matchupContestant2":"none","matchupOdds2":0,"isCircled":false,"splitBall":0,"handicap":[{"handicap":"2.5","handicapOdds":"-105"},{"handicap":"3.0","handicapOdds":"-130"},{"handicap":"3.5","handicapOdds":"-160"},{"handicap":"4.0","handicapOdds":"-175"},{"handicap":"4.5","handicapOdds":"-190"},{"handicap":"5.0","handicapOdds":"-205"}]},{"lineID":598097,"lineType":2,"isLineActive":true,"odds":-120,"overLineValue":"30.0","underLineValue":0,"pointSpreadValue":null,"alternateLineID":0,"matchupContestant1":"none","matchupOdds1":0,"matchupContestant2":"none","matchupOdds2":0,"isCircled":false,"splitBall":0,"handicap":[{"handicap":"29.5","handicapOdds":"-130"},{"handicap":"29.0","handicapOdds":"-140"},{"handicap":"28.5","handicapOdds":"-155"},{"handicap":"28.0","handicapOdds":"-170"},{"handicap":"27.5","handicapOdds":"-185"},{"handicap":"27.0","handicapOdds":"-200"}]},{"lineID":597839,"lineType":3,"isLineActive":true,"odds":100,"overLineValue":0,"underLineValue":"30.0","pointSpreadValue":null,"alternateLineID":0,"matchupContestant1":"none","matchupOdds1":0,"matchupContestant2":"none","matchupOdds2":0,"isCircled":false,"splitBall":0,"handicap":[{"handicap":"30.5","handicapOdds":"-110"},{"handicap":"31.0","handicapOdds":"-120"},{"handicap":"31.5","handicapOdds":"-135"},{"handicap":"32.0","handicapOdds":"-150"},{"handicap":"32.5","handicapOdds":"-165"},{"handicap":"33.0","handicapOdds":"-180"}]}]}]}]]